pyresolvemetrics/__init__.py
pyresolvemetrics/_algebraic.py
pyresolvemetrics/_probabilistic.py
pyresolvemetrics/_utils.py
pyresolvemetrics-0.3.5.dist-info/LICENSE
pyresolvemetrics-0.3.5.dist-info/METADATA
pyresolvemetrics-0.3.5.dist-info/WHEEL
pyresolvemetrics-0.3.5.dist-info/RECORD
