Metadata-Version: 2.1
Name: pyresolvemetrics
Version: 0.3.5
Summary: Entity resolution metrics library
Author: Andrei Olar
Author-email: andrei.olar@ubbcluj.ro
Requires-Python: >=3.12,<4.0
Classifier: Programming Language :: Python :: 3
Classifier: Programming Language :: Python :: 3.12
Classifier: Programming Language :: Python :: 3.13
Requires-Dist: numpy (>=2.2.4,<3.0.0)
